COPYING
MANIFEST.in
NEWS
README.md
dev-requirements.txt
requirements.txt
setup.py
sopel_modules/__init__.py
sopel_modules.stats.egg-info/PKG-INFO
sopel_modules.stats.egg-info/SOURCES.txt
sopel_modules.stats.egg-info/dependency_links.txt
sopel_modules.stats.egg-info/namespace_packages.txt
sopel_modules.stats.egg-info/requires.txt
sopel_modules.stats.egg-info/top_level.txt
sopel_modules/stats/__init__.py
sopel_modules/stats/stats.py
tests/__init__.py
tests/test_stats.py