Metadata-Version: 1.0
Name: sopel-modules.stats
Version: 0.1
Summary: Advanced stats tracking module for Sopel IRC bot
Home-page: http://github.com/minsis/sopel-stats
Author: Dennis Whitney
Author-email: dwhitney@irunasroot.com
License: Eiffel Forum License, version 2
Platform: UNKNOWN
